llm_sandbox/__init__.py
llm_sandbox/const.py
llm_sandbox/data.py
llm_sandbox/docker.py
llm_sandbox/exceptions.py
llm_sandbox/interactive.py
llm_sandbox/k8s_utils.py
llm_sandbox/kubernetes.py
llm_sandbox/micromamba.py
llm_sandbox/podman.py
llm_sandbox/security.py
llm_sandbox/session.py
llm_sandbox/core/__init__.py
llm_sandbox/core/config.py
llm_sandbox/core/mixins.py
llm_sandbox/core/session_base.py
llm_sandbox/language_handlers/__init__.py
llm_sandbox/language_handlers/base.py
llm_sandbox/language_handlers/cpp_handler.py
llm_sandbox/language_handlers/factory.py
llm_sandbox/language_handlers/go_handler.py
llm_sandbox/language_handlers/java_handler.py
llm_sandbox/language_handlers/javascript_handler.py
llm_sandbox/language_handlers/python_handler.py
llm_sandbox/language_handlers/r_handler.py
llm_sandbox/language_handlers/ruby_handler.py
llm_sandbox/language_handlers/runtime_context.py
llm_sandbox/language_handlers/artifact_detection/__init__.py
llm_sandbox/language_handlers/artifact_detection/python_plot_detection.py
llm_sandbox/language_handlers/artifact_detection/r_plot_detection.py
llm_sandbox/mcp_server/__init__.py
llm_sandbox/mcp_server/const.py
llm_sandbox/mcp_server/server.py
llm_sandbox/mcp_server/types.py
llm_sandbox/pool/__init__.py
llm_sandbox/pool/base.py
llm_sandbox/pool/config.py
llm_sandbox/pool/docker_pool.py
llm_sandbox/pool/exceptions.py
llm_sandbox/pool/factory.py
llm_sandbox/pool/kubernetes_pool.py
llm_sandbox/pool/podman_pool.py
llm_sandbox/pool/session.py
llm_sandbox-0.3.31.dist-info/METADATA
llm_sandbox-0.3.31.dist-info/WHEEL
llm_sandbox-0.3.31.dist-info/licenses/LICENSE
llm_sandbox-0.3.31.dist-info/RECORD
