Metadata-Version: 2.4
Name: llm-sandbox
Version: 0.3.31
Summary: LLM Sandbox is a lightweight and portable sandbox environment designed to run large language model (LLM) generated code in a safe and isolated mode.
Project-URL: Homepage, https://vndee.github.io/llm-sandbox/
Project-URL: Repository, https://github.com/vndee/llm-sandbox
Project-URL: Documentation, https://vndee.github.io/llm-sandbox/
Author-email: Duy Huynh <vndee.huynh@gmail.com>
License-File: LICENSE
Keywords: python
Classifier: Intended Audience :: Developers
Classifier: Programming Language :: Python
Classifier: Programming Language :: Python :: 3.10
Classifier: Programming Language :: Python :: 3.11
Classifier: Programming Language :: Python :: 3.12
Classifier: Programming Language :: Python :: 3.13
Classifier: Topic :: Software Development :: Libraries :: Python Modules
Requires-Python: <4.0,>=3.10
Requires-Dist: pydantic>=2.11.5
Provides-Extra: docker
Requires-Dist: docker>=7.1.0; extra == 'docker'
Provides-Extra: k8s
Requires-Dist: kubernetes>=32.0.1; extra == 'k8s'
Provides-Extra: mcp-docker
Requires-Dist: docker>=7.1.0; extra == 'mcp-docker'
Requires-Dist: mcp>=1.10.0; extra == 'mcp-docker'
Provides-Extra: mcp-k8s
Requires-Dist: kubernetes>=32.0.1; extra == 'mcp-k8s'
Requires-Dist: mcp>=1.10.0; extra == 'mcp-k8s'
Provides-Extra: mcp-podman
Requires-Dist: docker>=7.1.0; extra == 'mcp-podman'
Requires-Dist: mcp>=1.10.0; extra == 'mcp-podman'
Requires-Dist: podman>=5.4.0.1; extra == 'mcp-podman'
Provides-Extra: podman
Requires-Dist: docker>=7.1.0; extra == 'podman'
Requires-Dist: podman>=5.4.0.1; extra == 'podman'
